{
  "GameInfo": {
      "GameName": "Terminator 2",
      "System": "WPC",
      "FileVer": 1
  },
  "Definition": {
      "version": 1
  },
  "Memory": {
      "Start": 1,
      "Length": 8192,
      "NvStart": 2048,
      "NvLength": 2048
  },
  "BallInPlay": {
      "Type": 1,
      "Address": 950,
      "Ball1": 1,
      "Ball2": 2,
      "Ball3": 3,
      "Ball4": 4,
      "Ball5": 5
  },
  "DisplayMessage": {
      "Type": 10,
      "AddressS1": 7552,
      "AddressS2": 7617,
      "AddressS3": 7682,
      "Length": 32,
      "ChecksumStartAdr": 7552,
      "ChecksumEndAdr": 7744,
      "ChecksumResultAdr": 7745
  },
  "Adjustments": {
      "Type": 10,
      "CustomMessageOn": 6982,
      "ChecksumStartAdr": 6941,
      "ChecksumEndAdr": 7160,
      "ChecksumResultAdr": 7161
  },
  "HighScores": {
      "Type": 10,
      "ScoreAdr": 7268,
      "BytesInScore": 5,
      "ScoreSpacing": 8,
      "InitialAdr": 7265,
      "InitialSpacing": 8,
      "NumberOfScores": 4,
      "GrandChampScoreAdr": 7302,
      "GrandChampInitAdr": 7299,
      "ChecksumStartAdr": 7265,
      "ChecksumEndAdr": 7296,
      "ChecksumResultAdr": 7297,
      "GCChecksumStartAdr": 7299,
      "GCChecksumEndAdr": 7306,
      "GCChecksumResultAdr": 7307
  },
  "HSRewards": {
      "Type": 0,
      "HS1": 0,
      "HS2": 0,
      "HS3": 0,
      "HS4": 0,
      "HS5": 0,
      "DisableByte": 0
  },
  "InPlay": {
      "Type": 10,
      "GameActiveAdr": 135,
      "GameActiveValue": 0,
      "Players": 6036,
      "PlayerUp": 1039,
      "ScoreAdr": 5936,
      "ScoreBytes": 5,
      "ScoreSpacing": 6
  },
  "Switches": {
    "Type": 10,
    "Address": 5975,
    "Length": 56,
    "Names": [
      ["Right Flipper", 60],
      ["Left Flipper", 60],
      ["Start Button", 60],
      ["Plumb Bob Tilt", 250],
      ["Trough Left", 60],
      ["Trough Center", 60],
      ["Trough Right", 60],
      ["Outhole", 60],

      ["Slam Tilt", 0],
      ["Coin Door Closed", 60],
      ["Ticket Dispenser", 0],
      ["Test Position Always Closed", 0],
      ["Left Outlane", 60],
      ["Left Return Lane", 60],
      ["Right Return Lane", 60],
      ["Right Outlane", 60],

      ["Gun Loaded", 60],
      ["Gun Mark", 60],
      ["Gun Home", 60],
      ["Grip Trigger", 60],
      [],
      ["Mid Left Standup Target", 60],
      ["Mid Center Standup Target", 60],
      ["Mid Right Standup Target", 60],

      ["Left Jet", 60],
      ["Right Jet", 60],
      ["Bottom Jet", 60],
      ["Left Sling", 60],
      ["Right Sling", 60],
      ["Top Right Standup Target", 60],
      ["Mid Right Standup Target", 60],
      ["Bottom Right Standup Target", 60],

      ["Left Lock", 60],
      [],
      ["Low Escape Route", 60],
      ["High Escape Route", 60],
      ["Top Lock", 60],
      ["Top Lane Left", 60],
      ["Top Lane Center", 60],
      ["Top Lane Right", 60],

      ["Left Ramp Entry", 60],
      ["Left Ramp Made", 60],
      ["Right Ramp Entry", 60],
      ["Right Ramp Made", 60],
      ["Low Chase Loop", 60],
      ["High Chase Loop", 60],
      [],
      [],

      ["Target 1 High", 60],
      ["Target 2", 60],
      ["Target 3", 60],
      ["Target 4", 60],
      ["Target 5 Low", 60],
      ["Ball Popper", 60],
      ["Drop Target", 60],
      ["Shooter", 60]
    ]
  }
}